tellox/__init__.py
tellox/pilot.py
tellox/utils.py
tellox-0.2.7.dist-info/LICENSE
tellox-0.2.7.dist-info/METADATA
tellox-0.2.7.dist-info/WHEEL
tellox-0.2.7.dist-info/RECORD
