Metadata-Version: 2.1
Name: tellox
Version: 0.2.7
Summary: The easy way to control a DJI Tello drone.
License: MIT
Keywords: tello,drone,dji,robotics,control
Author: Charles Dawson
Author-email: charles.dwsn@gmail.com
Requires-Python: >=3.9,<3.13
Classifier: Framework :: Robot Framework :: Library
Classifier: License :: OSI Approved :: MIT License
Classifier: Programming Language :: Python :: 3
Classifier: Programming Language :: Python :: 3.9
Classifier: Programming Language :: Python :: 3.10
Classifier: Programming Language :: Python :: 3.11
Classifier: Topic :: System :: Hardware
Requires-Dist: djitellopy (>=2.5.0,<3.0.0)
Requires-Dist: matplotlib (>=3.7.2,<4.0.0)
Requires-Dist: numpy (>=1.25.2,<2.0.0)
Requires-Dist: opencv-python (>=4.8.0.76,<5.0.0.0)
Requires-Dist: pandas (>=2.0.3,<3.0.0)
Requires-Dist: pupil-apriltags (>=1.0.4.post10,<2.0.0)
Requires-Dist: scipy (>=1.11.2,<2.0.0)
